{
  "module_id": "class8_math_ch12_concept_3",
  "module_title": "ಮರುಗುಂಪು ಮಾಡುವುದರಿಂದ ಅಪವರ್ತಿಸುವಿಕೆ",
  "class": "8",
  "chapter": "12",
  "chapter_title": "ಅಪವರ್ತಿಸುವಿಕೆ",
  "domain": "ಬೀಜಗಣಿತ",
  "prerequisites": [
    "class8_math_ch12_concept_1",
    "class8_math_ch12_concept_2"
  ],
  "theory": {
    "concept_summary": "ಮರುಗುಂಪು ಮಾಡುವಿಕೆ ಎಂದರೆ, ಬೀಜೋಕ್ತಿಯ ಎಲ್ಲಾ ಪದಗಳಲ್ಲಿ ಸಾಮಾನ್ಯ ಅಪವರ್ತನ ಇಲ್ಲದಿದ್ದಾಗ, ಪದಗಳನ್ನು ಸೂಕ್ತ ಗುಂಪುಗಳಾಗಿ ವಿಂಗಡಿಸಿ, ಪ್ರತಿ ಗುಂಪಿನಿಂದ ಸಾಮಾನ್ಯ ಅಪವರ್ತನವನ್ನು ಹೊರತೆಗೆಯುವ ವಿಧಾನ. ಇದು ಸಾಮಾನ್ಯ ಅಪವರ್ತನ ವಿಧಾನದ ವಿಸ್ತರಣೆಯಾಗಿದ್ದು, ಅಂತಿಮವಾಗಿ ಸಾಮಾನ್ಯ ದ್ವಿಪದ ಅಪವರ್ತನವನ್ನು ಹೊರತೆಗೆಯುವ ಮೂಲಕ ಅಪವರ್ತಿಸಲಾಗುತ್ತದೆ.",
    "definitions": [
      {
        "term": "ಮರುಗುಂಪು ಮಾಡುವಿಕೆ",
        "definition": "ಒಂದು ಬೀಜೋಕ್ತಿಯ ಎಲ್ಲಾ ಪದಗಳಿಗೂ ಯಾವುದೇ ಸಾಮಾನ್ಯ ಅಪವರ್ತನ ಇಲ್ಲದಿದ್ದಾಗ, ಪದಗಳನ್ನು ಸೂಕ್ತ ಗುಂಪುಗಳಾಗಿ ವಿಂಗಡಿಸಿ, ಪ್ರತಿ ಗುಂಪಿನಿಂದ ಸಾಮಾನ್ಯ ಅಪವರ್ತನವನ್ನು ಹೊರತೆಗೆಯುವ ವಿಧಾನ."
      }
    ],
    "formulas": [],
    "theorems": [],
    "properties": [],
    "visual_aids": []
  },
  "worked_examples": [
    {
      "example_id": "class8_math_ch12_example_4",
      "difficulty": "intermediate",
      "problem": "`2xy + 2y + 3x + 3` ನ್ನು ಅಪವರ್ತಿಸಿ.",
      "steps": [
        {
          "step": 1,
          "action": "ಪದಗಳನ್ನು ಗುಂಪುಗಳಾಗಿ ವಿಂಗಡಿಸಿ. ಮೊದಲ ಎರಡು ಪದಗಳು ಮತ್ತು ಕೊನೆಯ ಎರಡು ಪದಗಳನ್ನು ಗುಂಪು ಮಾಡಿ.",
          "justification": "ಮೊದಲ ಗುಂಪಿನಲ್ಲಿ `2y` ಮತ್ತು ಎರಡನೇ ಗುಂಪಿನಲ್ಲಿ `3` ಸಾಮಾನ್ಯ ಅಪವರ್ತನಗಳಿವೆ."
        },
        {
          "step": 2,
          "action": "ಪ್ರತಿ ಗುಂಪಿನಿಂದ ಸಾಮಾನ್ಯ ಅಪವರ್ತನವನ್ನು ಹೊರತೆಗೆಯಿರಿ.",
          "justification": "ಸಾಮಾನ್ಯ ಅಪವರ್ತನ ವಿಧಾನವನ್ನು ಪ್ರತಿ ಗುಂಪಿಗೆ ಅನ್ವಯಿಸುವುದು."
        },
        {
          "step": 3,
          "action": "ಹೊಸದಾಗಿ ಉಂಟಾದ ಸಾಮಾನ್ಯ ದ್ವಿಪದ ಅಪವರ್ತನ `(x + 1)` ನ್ನು ಹೊರತೆಗೆಯಿರಿ.",
          "justification": "ಈಗ `(x+1)` ಎರಡೂ ಪದಗಳಲ್ಲಿ ಸಾಮಾನ್ಯವಾಗಿದೆ."
        }
      ],
      "result": "ಅಪವರ್ತಿಸಿದ ರೂಪ: `(x + 1)(2y + 3)`.",
      "common_trap": "ಪದಗಳನ್ನು ಬೇರೆ ರೀತಿಯಲ್ಲಿಯೂ ಗುಂಪು ಮಾಡಬಹುದು. ಉದಾಹರಣೆಗೆ, `(2xy + 3x) + (2y + 3) = x(2y + 3) + 1(2y + 3) = (2y + 3)(x + 1)`. ಫಲಿತಾಂಶ ಒಂದೇ ಆಗಿರುತ್ತದೆ."
    },
    {
      "example_id": "class8_math_ch12_example_5",
      "difficulty": "intermediate",
      "problem": "`6xy - 4y + 6 - 9x` ನ್ನು ಅಪವರ್ತಿಸಿ.",
      "steps": [
        {
          "step": 1,
          "action": "ಪದಗಳನ್ನು ಮರುಜೋಡಣೆ ಮಾಡಿ ಗುಂಪು ಮಾಡಿ. `6xy` ಮತ್ತು `-4y` ಒಂದು ಗುಂಪು, `+6` ಮತ್ತು `-9x` ಇನ್ನೊಂದು ಗುಂಪು.",
          "justification": "ಸಾಮಾನ್ಯ ಅಪವರ್ತನಗಳನ್ನು ಪಡೆಯಲು ಅನುಕೂಲವಾಗುವಂತೆ ಜೋಡಿಸುವುದು."
        },
        {
          "step": 2,
          "action": "ಮೊದಲ ಗುಂಪಿನಿಂದ `2y` ನ್ನು ಸಾಮಾನ್ಯ ಅಪವರ್ತನವಾಗಿ ಹೊರತೆಗೆಯಿರಿ.",
          "justification": "None"
        },
        {
          "step": 3,
          "action": "ಎರಡನೇ ಗುಂಪನ್ನು `-9x + 6` ಎಂದು ಬರೆದು, `-3` ನ್ನು ಸಾಮಾನ್ಯ ಅಪವರ್ತನವಾಗಿ ಹೊರತೆಗೆಯಿರಿ.",
          "justification": "ಮೊದಲ ಗುಂಪಿನಲ್ಲಿ ಸಿಕ್ಕಿದ `(3x - 2)` ಅಪವರ್ತನವನ್ನೇ ಎರಡನೇ ಗುಂಪಿನಲ್ಲೂ ಪಡೆಯಲು ಋಣಾತ್ಮಕ ಸಂಖ್ಯೆಯನ್ನು ಹೊರತೆಗೆಯುವುದು ಅಗತ್ಯ."
        },
        {
          "step": 4,
          "action": "ಎರಡೂ ಭಾಗಗಳನ್ನು ಒಟ್ಟುಗೂಡಿಸಿ, ಸಾಮಾನ್ಯ ದ್ವಿಪದ ಅಪವರ್ತನ `(3x - 2)` ನ್ನು ಹೊರತೆಗೆಯಿರಿ.",
          "justification": "None"
        }
      ],
      "result": "ಅಪವರ್ತಿಸಿದ ರೂಪ: `(3x - 2)(2y - 3)`.",
      "common_trap": null
    }
  ],
  "exam_intelligence": {
    "gpstr_weightage": "medium",
    "mcq_note": "ಅಪವರ್ತಿಸುವಿಕೆಯ ಒಂದು ಹಂತವನ್ನು ನೀಡಿ, ಮುಂದಿನ ಹಂತವನ್ನು ಕೇಳಬಹುದು.",
    "two_mark_note": "ನಾಲ್ಕು ಪದಗಳಿರುವ ಬೀಜೋಕ್ತಿಯನ್ನು ಮರುಗುಂಪು ಮಾಡಿ ಅಪವರ್ತಿಸಲು ಕೇಳಬಹುದು.",
    "five_mark_note": "ಇಲ್ಲ.",
    "common_mistakes": [
      "ಋಣಾತ್ಮಕ ಚಿಹ್ನೆಯನ್ನು ಸಾಮಾನ್ಯ ಅಪವರ್ತನವಾಗಿ ಹೊರತೆಗೆಯುವಾಗ ಆವರಣದೊಳಗಿನ ಪದಗಳ ಚಿಹ್ನೆಗಳನ್ನು ಬದಲಾಯಿಸಲು ಮರೆಯುವುದು. ಉದಾಹರಣೆಗೆ, `6 - 9x` ನಿಂದ `3` ನ್ನು ಹೊರತೆಗೆದು `3(2 - 3x)` ಎಂದು ಬರೆಯುವುದು, ಆದರೆ ನಮಗೆ `(3x - 2)` ಬೇಕಾಗಿರುವುದರಿಂದ `-3` ನ್ನು ಹೊರತೆಗೆಯಬೇಕು."
    ],
    "boundary_conditions": [],
    "connects_to": []
  }
}